shared_memory_deque/__init__.py
shared_memory_deque/deque.py
shared_memory_deque-0.1.dist-info/LICENSE.md
shared_memory_deque-0.1.dist-info/METADATA
shared_memory_deque-0.1.dist-info/WHEEL
shared_memory_deque-0.1.dist-info/top_level.txt
shared_memory_deque-0.1.dist-info/RECORD
