Metadata-Version: 2.1
Name: shared-memory-deque
Version: 0.1
Summary: a deque like implementation using multiprocessing.shared_memory
Home-page: https://github.com/cloasdata/shared-memory-deque
Author: Simon Bauer
Author-email: code@seimenadventure.de
License: MIT
Keywords: multiprocessing,queue,shared-memory
Classifier: Programming Language :: Python :: 3
Classifier: License :: OSI Approved :: MIT License
Classifier: Operating System :: OS Independent
License-File: LICENSE.md
Requires-Dist: importlib ; python_version >= "3.10"
Provides-Extra: test
Requires-Dist: pytest (>=7.0.0) ; extra == 'test'
